[
  {
    "city": "Los Angeles",
    "state": "California", 
    "stateCode": "CA",
    "slug": "los-angeles",
    "stateSlug": "california",
    "population": 3971000,
    "ruralArea": false,
    "avgPrice": "$175-225",
    "climate": "Mediterranean",
    "zipCodes": ["90001", "90210", "90211"],
    "nearbyFarms": 23,
    "farmingContext": "urban hobby farms and petting zoos",
    "regionalNotes": "Year-round outdoor goat keeping with minimal weather challenges",
    "majorNearbyCities": ["Pasadena", "Santa Monica", "Long Beach"]
  },
  {
    "city": "New York",
    "state": "New York",
    "stateCode": "NY", 
    "slug": "new-york",
    "stateSlug": "new-york",
    "population": 8336000,
    "ruralArea": false,
    "avgPrice": "$200-275",
    "climate": "Humid continental",
    "zipCodes": ["10001", "10019", "10128"],
    "nearbyFarms": 12,
    "farmingContext": "urban farms and educational centers",
    "regionalNotes": "Seasonal housing changes affect hoof moisture and growth patterns",
    "majorNearbyCities": ["Brooklyn", "Queens", "Jersey City"]
  },
  {
    "city": "Austin",
    "state": "Texas",
    "stateCode": "TX",
    "slug": "austin",
    "stateSlug": "texas", 
    "population": 965000,
    "ruralArea": false,
    "avgPrice": "$125-175",
    "climate": "Humid subtropical",
    "zipCodes": ["78701", "78745", "78759"],
    "nearbyFarms": 87,
    "farmingContext": "suburban homesteads and commercial goat operations",
    "regionalNotes": "Hot summers and mild winters create year-round grazing conditions",
    "majorNearbyCities": ["Round Rock", "Cedar Park", "Pflugerville"]
  },
  {
    "city": "Denver",
    "state": "Colorado",
    "stateCode": "CO",
    "slug": "denver", 
    "stateSlug": "colorado",
    "population": 715000,
    "ruralArea": false,
    "avgPrice": "$140-190",
    "climate": "Semi-arid",
    "zipCodes": ["80202", "80218", "80231"],
    "nearbyFarms": 156,
    "farmingContext": "mountain homesteads and foothills ranches",
    "regionalNotes": "High altitude and dry conditions require different hoof care approach",
    "majorNearbyCities": ["Aurora", "Lakewood", "Westminster"]
  },
  {
    "city": "Atlanta",
    "state": "Georgia",
    "stateCode": "GA",
    "slug": "atlanta",
    "stateSlug": "georgia",
    "population": 498000,
    "ruralArea": false,
    "avgPrice": "$110-160",
    "climate": "Humid subtropical",
    "zipCodes": ["30309", "30318", "30327"],
    "nearbyFarms": 234,
    "farmingContext": "suburban farms and agricultural education programs",
    "regionalNotes": "High humidity and warm temperatures promote faster hoof growth",
    "majorNearbyCities": ["Marietta", "Roswell", "Decatur"]
  },
  {
    "city": "Phoenix",
    "state": "Arizona",
    "stateCode": "AZ", 
    "slug": "phoenix",
    "stateSlug": "arizona",
    "population": 1680000,
    "ruralArea": false,
    "avgPrice": "$120-170",
    "climate": "Hot desert",
    "zipCodes": ["85001", "85018", "85032"],
    "nearbyFarms": 78,
    "farmingContext": "desert homesteads and heat-adapted operations",
    "regionalNotes": "Extreme heat and low humidity create hard, brittle hoof conditions",
    "majorNearbyCities": ["Scottsdale", "Tempe", "Mesa"]
  },
  {
    "city": "Seattle",
    "state": "Washington",
    "stateCode": "WA",
    "slug": "seattle",
    "stateSlug": "washington",
    "population": 750000,
    "ruralArea": false,
    "avgPrice": "$160-210",
    "climate": "Oceanic",
    "zipCodes": ["98101", "98115", "98125"],
    "nearbyFarms": 145,
    "farmingContext": "Pacific Northwest farms and sustainable agriculture operations",
    "regionalNotes": "Wet climate creates soft hooves prone to rot and fungal issues",
    "majorNearbyCities": ["Bellevue", "Tacoma", "Everett"]
  },
  {
    "city": "Chicago",
    "state": "Illinois",
    "stateCode": "IL",
    "slug": "chicago",
    "stateSlug": "illinois", 
    "population": 2746000,
    "ruralArea": false,
    "avgPrice": "$145-195",
    "climate": "Humid continental",
    "zipCodes": ["60601", "60614", "60647"],
    "nearbyFarms": 89,
    "farmingContext": "urban agriculture and educational farms",
    "regionalNotes": "Cold winters require barn housing which affects hoof moisture levels",
    "majorNearbyCities": ["Naperville", "Aurora", "Rockford"]
  },
  {
    "city": "Miami",
    "state": "Florida",
    "stateCode": "FL",
    "slug": "miami",
    "stateSlug": "florida",
    "population": 442000,
    "ruralArea": false,
    "avgPrice": "$135-185",
    "climate": "Tropical",
    "zipCodes": ["33101", "33131", "33156"],
    "nearbyFarms": 67,
    "farmingContext": "tropical hobby farms and agricultural education centers",
    "regionalNotes": "High humidity and heat create rapid hoof growth and fungal concerns",
    "majorNearbyCities": ["Fort Lauderdale", "Hialeah", "Coral Gables"]
  },
  {
    "city": "Portland",
    "state": "Oregon",
    "stateCode": "OR",
    "slug": "portland", 
    "stateSlug": "oregon",
    "population": 650000,
    "ruralArea": false,
    "avgPrice": "$150-200",
    "climate": "Oceanic",
    "zipCodes": ["97201", "97209", "97266"],
    "nearbyFarms": 178,
    "farmingContext": "sustainable farms and urban homesteads",
    "regionalNotes": "Wet climate similar to Seattle with soft hoof challenges",
    "majorNearbyCities": ["Beaverton", "Gresham", "Lake Oswego"]
  },
  {
    "city": "Nashville",
    "state": "Tennessee",
    "stateCode": "TN",
    "slug": "nashville",
    "stateSlug": "tennessee",
    "population": 695000,
    "ruralArea": false,
    "avgPrice": "$105-155",
    "climate": "Humid subtropical",
    "zipCodes": ["37201", "37205", "37211"],
    "nearbyFarms": 267,
    "farmingContext": "traditional Southern farms and homesteads",
    "regionalNotes": "Moderate climate with hot, humid summers requiring frequent trimming",
    "majorNearbyCities": ["Franklin", "Murfreesboro", "Hendersonville"]
  },
  {
    "city": "Salt Lake City",
    "state": "Utah",
    "stateCode": "UT",
    "slug": "salt-lake-city",
    "stateSlug": "utah",
    "population": 200000,
    "ruralArea": false,
    "avgPrice": "$125-175",
    "climate": "Semi-arid",
    "zipCodes": ["84101", "84103", "84116"],
    "nearbyFarms": 134,
    "farmingContext": "mountain valley farms and hobby ranches",
    "regionalNotes": "Dry climate and altitude create unique hoof care needs",
    "majorNearbyCities": ["West Valley City", "Provo", "West Jordan"]
  },
  {
    "city": "Boise",
    "state": "Idaho",
    "stateCode": "ID",
    "slug": "boise",
    "stateSlug": "idaho",
    "population": 235000,
    "ruralArea": false,
    "avgPrice": "$115-165",
    "climate": "Semi-arid",
    "zipCodes": ["83702", "83704", "83713"],
    "nearbyFarms": 203,
    "farmingContext": "agricultural valley farms and rural homesteads",
    "regionalNotes": "Four-season climate with cold winters affecting hoof condition",
    "majorNearbyCities": ["Meridian", "Nampa", "Caldwell"]
  },
  {
    "city": "Oklahoma City",
    "state": "Oklahoma",
    "stateCode": "OK",
    "slug": "oklahoma-city",
    "stateSlug": "oklahoma",
    "population": 695000,
    "ruralArea": false,
    "avgPrice": "$95-145",
    "climate": "Humid subtropical",
    "zipCodes": ["73102", "73112", "73135"],
    "nearbyFarms": 456,
    "farmingContext": "Great Plains ranches and agricultural operations",
    "regionalNotes": "Variable weather and frequent storms affect outdoor goat management",
    "majorNearbyCities": ["Norman", "Edmond", "Midwest City"]
  },
  {
    "city": "Kansas City",
    "state": "Missouri",
    "stateCode": "MO",
    "slug": "kansas-city",
    "stateSlug": "missouri", 
    "population": 508000,
    "ruralArea": false,
    "avgPrice": "$100-150",
    "climate": "Humid continental",
    "zipCodes": ["64108", "64111", "64130"],
    "nearbyFarms": 312,
    "farmingContext": "Midwest agricultural operations and family farms",
    "regionalNotes": "Hot summers and cold winters create seasonal hoof care challenges",
    "majorNearbyCities": ["Independence", "Overland Park", "Lee's Summit"]
  },
  {
    "city": "San Antonio",
    "state": "Texas",
    "stateCode": "TX",
    "slug": "san-antonio",
    "stateSlug": "texas",
    "population": 1547000,
    "ruralArea": false,
    "avgPrice": "$115-165",
    "climate": "Humid subtropical",
    "zipCodes": ["78201", "78217", "78245"],
    "nearbyFarms": 312,
    "farmingContext": "South Texas ranches and livestock operations",
    "regionalNotes": "Hot climate requires shade management and frequent water access",
    "majorNearbyCities": ["New Braunfels", "Schertz", "Universal City"]
  },
  {
    "city": "Sacramento",
    "state": "California",
    "stateCode": "CA",
    "slug": "sacramento",
    "stateSlug": "california",
    "population": 525000,
    "ruralArea": false,
    "avgPrice": "$160-210",
    "climate": "Mediterranean",
    "zipCodes": ["95814", "95821", "95828"],
    "nearbyFarms": 456,
    "farmingContext": "Central Valley agricultural operations and dairies",
    "regionalNotes": "Hot, dry summers ideal for most goat breeds",
    "majorNearbyCities": ["Roseville", "Elk Grove", "Davis"]
  },
  {
    "city": "Fresno",
    "state": "California",
    "stateCode": "CA",
    "slug": "fresno",
    "stateSlug": "california",
    "population": 542000,
    "ruralArea": false,
    "avgPrice": "$140-190",
    "climate": "Hot semi-arid",
    "zipCodes": ["93701", "93720", "93730"],
    "nearbyFarms": 789,
    "farmingContext": "Central Valley farm operations and large dairies",
    "regionalNotes": "Intense summer heat requires careful hoof monitoring",
    "majorNearbyCities": ["Clovis", "Madera", "Selma"]
  },
  {
    "city": "Richmond",
    "state": "Virginia",
    "stateCode": "VA",
    "slug": "richmond",
    "stateSlug": "virginia",
    "population": 230000,
    "ruralArea": false,
    "avgPrice": "$125-175",
    "climate": "Humid subtropical",
    "zipCodes": ["23220", "23225", "23235"],
    "nearbyFarms": 234,
    "farmingContext": "Virginia horse farms and small livestock operations",
    "regionalNotes": "Moderate climate with seasonal adjustments needed",
    "majorNearbyCities": ["Mechanicsville", "Glen Allen", "Chesterfield"]
  },
  {
    "city": "Raleigh",
    "state": "North Carolina",
    "stateCode": "NC",
    "slug": "raleigh",
    "stateSlug": "north-carolina",
    "population": 470000,
    "ruralArea": false,
    "avgPrice": "$115-165",
    "climate": "Humid subtropical",
    "zipCodes": ["27601", "27612", "27615"],
    "nearbyFarms": 345,
    "farmingContext": "Research Triangle area farms and educational operations",
    "regionalNotes": "Mild winters allow year-round outdoor keeping",
    "majorNearbyCities": ["Durham", "Cary", "Chapel Hill"]
  },
  {
    "city": "Columbus",
    "state": "Ohio",
    "stateCode": "OH",
    "slug": "columbus",
    "stateSlug": "ohio",
    "population": 898000,
    "ruralArea": false,
    "avgPrice": "$105-155",
    "climate": "Humid continental",
    "zipCodes": ["43215", "43229", "43235"],
    "nearbyFarms": 267,
    "farmingContext": "Ohio agricultural belt farms and 4-H operations",
    "regionalNotes": "Cold winters require barn housing and moisture management",
    "majorNearbyCities": ["Dublin", "Westerville", "Grove City"]
  },
  {
    "city": "Des Moines",
    "state": "Iowa",
    "stateCode": "IA",
    "slug": "des-moines",
    "stateSlug": "iowa",
    "population": 215000,
    "ruralArea": false,
    "avgPrice": "$95-145",
    "climate": "Humid continental",
    "zipCodes": ["50309", "50315", "50320"],
    "nearbyFarms": 678,
    "farmingContext": "Corn Belt livestock and diversified farming operations",
    "regionalNotes": "Harsh winters require heated barns and dry bedding",
    "majorNearbyCities": ["West Des Moines", "Ankeny", "Urbandale"]
  },
  {
    "city": "Madison",
    "state": "Wisconsin",
    "stateCode": "WI",
    "slug": "madison",
    "stateSlug": "wisconsin",
    "population": 260000,
    "ruralArea": false,
    "avgPrice": "$110-160",
    "climate": "Humid continental",
    "zipCodes": ["53703", "53711", "53719"],
    "nearbyFarms": 456,
    "farmingContext": "Wisconsin dairy country and university research farms",
    "regionalNotes": "Long winters require extensive barn facilities",
    "majorNearbyCities": ["Middleton", "Sun Prairie", "Fitchburg"]
  },
  {
    "city": "Little Rock",
    "state": "Arkansas",
    "stateCode": "AR",
    "slug": "little-rock",
    "stateSlug": "arkansas",
    "population": 198000,
    "ruralArea": false,
    "avgPrice": "$90-140",
    "climate": "Humid subtropical",
    "zipCodes": ["72201", "72205", "72211"],
    "nearbyFarms": 567,
    "farmingContext": "Arkansas Delta agricultural operations and poultry farms",
    "regionalNotes": "Hot, humid summers accelerate hoof growth",
    "majorNearbyCities": ["North Little Rock", "Conway", "Jacksonville"]
  },
  {
    "city": "Omaha",
    "state": "Nebraska",
    "stateCode": "NE",
    "slug": "omaha",
    "stateSlug": "nebraska",
    "population": 486000,
    "ruralArea": false,
    "avgPrice": "$100-150",
    "climate": "Humid continental",
    "zipCodes": ["68102", "68114", "68124"],
    "nearbyFarms": 423,
    "farmingContext": "Great Plains cattle and grain operations",
    "regionalNotes": "Variable weather requires flexible housing solutions",
    "majorNearbyCities": ["Bellevue", "Papillion", "Council Bluffs"]
  },
  {
    "city": "Tulsa",
    "state": "Oklahoma",
    "stateCode": "OK",
    "slug": "tulsa",
    "stateSlug": "oklahoma",
    "population": 413000,
    "ruralArea": false,
    "avgPrice": "$95-145",
    "climate": "Humid subtropical",
    "zipCodes": ["74104", "74114", "74134"],
    "nearbyFarms": 512,
    "farmingContext": "Oklahoma grasslands and cattle ranching operations",
    "regionalNotes": "Tornado season requires secure shelter planning",
    "majorNearbyCities": ["Broken Arrow", "Owasso", "Bixby"]
  },
  {
    "city": "Wichita",
    "state": "Kansas",
    "stateCode": "KS",
    "slug": "wichita",
    "stateSlug": "kansas",
    "population": 396000,
    "ruralArea": false,
    "avgPrice": "$90-140",
    "climate": "Humid continental",
    "zipCodes": ["67202", "67212", "67226"],
    "nearbyFarms": 634,
    "farmingContext": "Kansas wheat belt and cattle operations",
    "regionalNotes": "High winds and temperature extremes affect housing needs",
    "majorNearbyCities": ["Derby", "Andover", "Maize"]
  },
  {
    "city": "Burlington",
    "state": "Vermont",
    "stateCode": "VT",
    "slug": "burlington",
    "stateSlug": "vermont",
    "population": 44000,
    "ruralArea": true,
    "avgPrice": "$135-185",
    "climate": "Humid continental",
    "zipCodes": ["05401", "05403", "05408"],
    "nearbyFarms": 234,
    "farmingContext": "Vermont dairy farms and sustainable agriculture operations",
    "regionalNotes": "Long, cold winters require extensive indoor housing",
    "majorNearbyCities": ["South Burlington", "Winooski", "Essex"]
  },
  {
    "city": "Billings",
    "state": "Montana",
    "stateCode": "MT",
    "slug": "billings",
    "stateSlug": "montana",
    "population": 117000,
    "ruralArea": true,
    "avgPrice": "$110-160",
    "climate": "Semi-arid",
    "zipCodes": ["59101", "59102", "59106"],
    "nearbyFarms": 445,
    "farmingContext": "Montana ranch country and livestock operations",
    "regionalNotes": "Extreme temperature swings require robust shelter",
    "majorNearbyCities": ["Laurel", "Shepherd", "Lockwood"]
  },
  {
    "city": "Fargo",
    "state": "North Dakota",
    "stateCode": "ND",
    "slug": "fargo",
    "stateSlug": "north-dakota",
    "population": 125000,
    "ruralArea": true,
    "avgPrice": "$100-150",
    "climate": "Humid continental",
    "zipCodes": ["58102", "58103", "58104"],
    "nearbyFarms": 378,
    "farmingContext": "Red River Valley agricultural operations",
    "regionalNotes": "Severe winters require heated facilities and dry conditions",
    "majorNearbyCities": ["West Fargo", "Moorhead", "Dilworth"]
  }
]